constellationpkgtools
