Metadata-Version: 1.1
Name: constellation-pkgtools-cli
Version: 1.0.6
Summary: Constellation Package Tools CLI
Home-page: https://developer.myconstellation.io
Author: Sebastien Warin
Author-email: support@myconstellation.io
License: Apache
Keywords: constellation package python tools development
Platform: UNKNOWN
Classifier: Development Status :: 5 - Production/Stable
Classifier: Intended Audience :: Developers
Classifier: Topic :: Software Development :: Build Tools
Classifier: License :: OSI Approved :: Apache Software License
Classifier: Programming Language :: Python :: 2
Classifier: Programming Language :: Python :: 2.7
